qdsdk/__init__.py
qdsdk/aio_api.py
qdsdk/api.py
qdsdk/client.py
qdsdk/config.py
qdsdk/qedata.thrift
qdsdk/utils.py
qdsdk-0.0.5.dist-info/LICENSE
qdsdk-0.0.5.dist-info/METADATA
qdsdk-0.0.5.dist-info/WHEEL
qdsdk-0.0.5.dist-info/top_level.txt
qdsdk-0.0.5.dist-info/RECORD
