Metadata-Version: 2.1
Name: qdsdk
Version: 0.0.5
Summary: QuantDo SDK for quants
Author-email: Fisher Yu <yuzs@quantdo.com.cn>
License: MIT License
Project-URL: Homepage, https://doc.quantdo.com.cn/helpbook/index.html#/cn/qdsdk/0.0.1/README
Classifier: Programming Language :: Python :: 3
Classifier: License :: OSI Approved :: MIT License
Classifier: Operating System :: OS Independent
Requires-Python: >=3.7
License-File: LICENSE
Requires-Dist: msgpack-python >=0.5.6
Requires-Dist: nest-asyncio >=1.5.5
Requires-Dist: numpy >=1.19.2
Requires-Dist: pandas >=1.3.5
Requires-Dist: thriftpy2 >=0.4.14
